{
  "category": "codeLibrary",
  "chunkIndex": 4,
  "totalChunks": 29,
  "items": [
    "/code/structural-var",
    "/code/bayesian-var",
    "/code/tvp-var",
    "/code/nelson-siegel",
    "/code/dynamic-nelson-siegel",
    "/code/svensson-model",
    "/code/copula-models",
    "/code/gaussian-copula",
    "/code/student-t-copula",
    "/code/clayton-copula",
    "/code/gumbel-copula",
    "/code/frank-copula",
    "/code/vine-copula",
    "/code/dynamic-copula",
    "/code/lstm",
    "/code/gru",
    "/code/bilstm",
    "/code/transformer-time-series",
    "/code/informer",
    "/code/autoformer",
    "/code/fedformer",
    "/code/patchtst",
    "/code/timesnet",
    "/code/n-beats",
    "/code/deepar",
    "/code/tft",
    "/code/neural-prophet",
    "/code/etsformer",
    "/code/dlinear",
    "/code/filternet",
    "/code/micn",
    "/code/crossformer",
    "/code/stationary-transformer",
    "/code/wavelet-transform",
    "/code/hilbert-huang-transform",
    "/code/empirical-mode-decomposition",
    "/code/singular-spectrum-analysis",
    "/code/prophet",
    "/code/dynamic-factor-model",
    "/code/nowcasting-model",
    "/code/mixed-frequency-data",
    "/code/panel-var",
    "/code/bayesian-structural-time-series",
    "/code/gaussian-process",
    "/code/neural-ode",
    "/code/neural-sde",
    "/code/score-based-model",
    "/code/diffusion-model",
    "/code/normalizing-flow",
    "/code/variational-autoencoder",
    "/code/attention-mechanism",
    "/code/self-attention",
    "/code/cross-attention",
    "/code/multi-head-attention",
    "/code/sharpe-ratio",
    "/code/sortino-ratio",
    "/code/calmar-ratio",
    "/code/sterling-ratio",
    "/code/burke-ratio",
    "/code/omega-ratio"
  ],
  "parentPath": "/code",
  "chunkType": "base_paths",
  "languageChunkFile": "codeLibrary_languages.chunk-4-of-29.json"
}